blackduck_lutils/__about__.py
blackduck_lutils/__init__.py
blackduck_lutils/license_conflicts.py
blackduck_lutils/license_tagging.py
blackduck_lutils-0.0.20.dist-info/METADATA
blackduck_lutils-0.0.20.dist-info/WHEEL
blackduck_lutils-0.0.20.dist-info/licenses/LICENSE
blackduck_lutils-0.0.20.dist-info/RECORD
